pytest_simplified/__init__.py
pytest_simplified/plugin.py
pytest_simplified/suites/__init__.py
pytest_simplified/suites/attributes.py
pytest_simplified/suites/functions.py
pytest_simplified-1.0.0rc3.dist-info/licenses/LICENSE
pytest_simplified-1.0.0rc3.dist-info/METADATA
pytest_simplified-1.0.0rc3.dist-info/WHEEL
pytest_simplified-1.0.0rc3.dist-info/entry_points.txt
pytest_simplified-1.0.0rc3.dist-info/top_level.txt
pytest_simplified-1.0.0rc3.dist-info/RECORD
