Metadata-Version: 2.4
Name: pytest-simplified
Version: 1.0.0rc3
Summary: A PyTest plugin to simplify testing classes.
Author-email: No Fuss Computing <helpdesk@nofusscomputing.com>
Maintainer-email: No Fuss Computing <helpdesk@nofusscomputing.com>
License-Expression: AGPL-3.0-only
Project-URL: Changelog, https://github.com/nofusscomputing/pytest_simplified/blob/master/CHANGELOG.md
Project-URL: Homepage, https://nofusscomputing.com/git/pytest/simplified
Project-URL: Issues, https://nofusscomputing.com/git/pytest/simplified/issues
Project-URL: releasenotes, https://github.com/nofusscomputing/pytest_simplified/blob/master/Release-Notes.md
Project-URL: Source, https://nofusscomputing.com/git/pytest/simplified
Classifier: Development Status :: 4 - Beta
Classifier: Framework :: Pytest
Classifier: Intended Audience :: Developers
Classifier: Programming Language :: Python :: 3
Classifier: Programming Language :: Python :: 3 :: Only
Classifier: Programming Language :: Python :: 3.10
Classifier: Programming Language :: Python :: 3.11
Classifier: Programming Language :: Python :: 3.12
Classifier: Programming Language :: Python :: 3.13
Classifier: Operating System :: OS Independent
Requires-Python: >=3.10
License-File: LICENSE
Requires-Dist: pytest<9.0.0,>=8.3.5
Dynamic: license-file
